LICENSE
MANIFEST.in
README.rst
setup.py
django_shop_ipayment.egg-info/PKG-INFO
django_shop_ipayment.egg-info/SOURCES.txt
django_shop_ipayment.egg-info/dependency_links.txt
django_shop_ipayment.egg-info/not-zip-safe
django_shop_ipayment.egg-info/requires.txt
django_shop_ipayment.egg-info/top_level.txt
ipayment/__init__.py
ipayment/admin.py
ipayment/forms.py
ipayment/models.py
ipayment/offsite_backend.py
ipayment/tests.py
ipayment/views.py
ipayment/migrations/0001_initial.py
ipayment/migrations/0002_auto__del_confirmation.py
ipayment/migrations/0003_auto__add_confirmation.py
ipayment/migrations/__init__.py
ipayment/templates/.tmp_payment.html.89907~
ipayment/templates/payment.html
ipayment/templates/success.html