Metadata-Version: 1.0
Name: django-shop-ipayment
Version: 0.0.3
Summary: A payment backend module for django-SHOP, using IPayment (https://ipayment.de) from the 1und1 company in Germany.
Home-page: https://github.com/jrief/django-shop-ipayment
Author: Jacob Rief
Author-email: jacob.rief@gmail.com
License: BSD License
Keywords: django,django-shop,ipayment
Platform: OS Independent
Classifier: Development Status :: 3 - Alpha
Classifier: Environment :: Web Environment
Classifier: Framework :: Django
Classifier: Intended Audience :: Developers
Classifier: License :: OSI Approved :: BSD License
Classifier: Operating System :: OS Independent
Classifier: Programming Language :: Python
